README.md
setup.py
pyRecoverName/__init__.py
pyRecoverName.egg-info/PKG-INFO
pyRecoverName.egg-info/SOURCES.txt
pyRecoverName.egg-info/dependency_links.txt
pyRecoverName.egg-info/entry_points.txt
pyRecoverName.egg-info/requires.txt
pyRecoverName.egg-info/top_level.txt