Metadata-Version: 1.1
Name: pyRecoverName
Version: 0.1.0
Summary: A practical program designed for fixing the filename misencoded.
Home-page: https://github.com/xdusongwei/pyRecoverName
Author: 宋伟(songwei)
Author-email: songwei@songwei.io
License: MIT
Platform: UNKNOWN
Classifier: Development Status :: 4 - Beta
Classifier: Intended Audience :: Developers
Classifier: Programming Language :: Python :: 3
Classifier: Programming Language :: Python :: 3.3
Classifier: Programming Language :: Python :: 3.4
Classifier: Programming Language :: Python :: 3.5
Classifier: Programming Language :: Python :: 3.6
Classifier: Operating System :: Microsoft :: Windows
Classifier: Operating System :: POSIX
Classifier: Operating System :: Unix
Classifier: Operating System :: MacOS
